chatwolf/__init__.py
chatwolf/__main__.py
chatwolf/_conf.py
chatwolf/check_conf.py
chatwolf/game.py
chatwolf/gui.py
chatwolf/nightactions.py
chatwolf/player.py
chatwolf/roles.py
chatwolf/skypecommands.py
chatwolf/data/conf_root.json
chatwolf/data/icon.png
chatwolf/data/messages/en/ask.txt
chatwolf/data/messages/en/day_end.txt
chatwolf/data/messages/en/day_killed.txt
chatwolf/data/messages/en/day_start_all.txt
chatwolf/data/messages/en/end_intro.txt
chatwolf/data/messages/en/end_love.txt
chatwolf/data/messages/en/end_noone.txt
chatwolf/data/messages/en/end_villager.txt
chatwolf/data/messages/en/end_werewolfs.txt
chatwolf/data/messages/en/error_request.txt
chatwolf/data/messages/en/greeting_all.txt
chatwolf/data/messages/en/greeting_all_roles.txt
chatwolf/data/messages/en/greeting_amor.txt
chatwolf/data/messages/en/greeting_prostitute.txt
chatwolf/data/messages/en/greeting_start10s.txt
chatwolf/data/messages/en/greeting_villager.txt
chatwolf/data/messages/en/greeting_visionary.txt
chatwolf/data/messages/en/greeting_werewolf.txt
chatwolf/data/messages/en/greeting_witch.txt
chatwolf/data/messages/en/night_prostitute.txt
chatwolf/data/messages/en/night_resume.txt
chatwolf/data/messages/en/night_sleep.txt
chatwolf/data/messages/en/night_visionary.txt
chatwolf/data/messages/en/night_werewolf.txt
chatwolf/data/messages/en/night_witch.txt
chatwolf/data/messages/en/night_witch_kill.txt
chatwolf/data/messages/en/night_witch_kill_list.txt
chatwolf/data/messages/en/night_witch_noone.txt
chatwolf/data/messages/en/night_witch_save.txt
chatwolf/data/messages/en/player_arrow.txt
chatwolf/data/messages/en/welcome_player.txt
chatwolf/scripts/start_manualy.py
chatwolf-0.1.4.dist-info/LICENSE.txt
chatwolf-0.1.4.dist-info/METADATA
chatwolf-0.1.4.dist-info/WHEEL
chatwolf-0.1.4.dist-info/entry_points.txt
chatwolf-0.1.4.dist-info/top_level.txt
chatwolf-0.1.4.dist-info/RECORD
