Metadata-Version: 2.1
Name: chatwolf
Version: 0.1.4
Summary: An unofficial game, to play Werewolf on Skype
Home-page: https://github.com/maxschmi/chatwolf
Author: Max Schmit
Author-email: maxschm@hotmail.com
License: GPL-3.0-or-later
Project-URL: Github, https://github.com/maxschmi/chatwolf
Project-URL: Docs, https://chatwolf.readthedocs.io
Keywords: chat werewolf game multiplayer online skype
Platform: UNKNOWN
Classifier: Programming Language :: Python :: 3
Classifier: Development Status :: 3 - Alpha
Classifier: Environment :: Console
Classifier: Intended Audience :: End Users/Desktop
Classifier: License :: OSI Approved :: GNU General Public License v3 or later (GPLv3+)
Classifier: Natural Language :: English
Classifier: Topic :: Communications
Classifier: Topic :: Communications :: Chat
Classifier: Topic :: Communications :: Conferencing
Classifier: Topic :: Games/Entertainment
Classifier: Topic :: Games/Entertainment :: Role-Playing
Requires-Python: >=3
Requires-Dist: skpy
